glean/__init__.py
glean/_hooks/__init__.py
glean/_hooks/registration.py
glean/_hooks/sdkhooks.py
glean/_hooks/types.py
glean/_version.py
glean/activities.py
glean/agents.py
glean/announcements.py
glean/answers.py
glean/basesdk.py
glean/client.py
glean/client_activity.py
glean/client_authentication.py
glean/client_chat.py
glean/client_documents.py
glean/client_shortcuts.py
glean/client_verification.py
glean/collections.py
glean/datasources.py
glean/entities.py
glean/errors/__init__.py
glean/errors/collectionerror.py
glean/errors/gleandataerror.py
glean/errors/gleanerror.py
glean/httpclient.py
glean/indexing.py
glean/indexing_authentication.py
glean/indexing_documents.py
glean/indexing_permissions.py
glean/indexing_shortcuts.py
glean/insights.py
glean/messages.py
glean/models/__init__.py
glean/models/activity.py
glean/models/activityevent.py
glean/models/activityeventparams.py
glean/models/addcollectionitemserror.py
glean/models/addcollectionitemsop.py
glean/models/addcollectionitemsrequest.py
glean/models/addcollectionitemsresponse.py
glean/models/additionalfielddefinition.py
glean/models/addverificationreminderop.py
glean/models/adminsearchop.py
glean/models/agent.py
glean/models/agentconfig.py
glean/models/agentresult.py
glean/models/aiappactioncounts.py
glean/models/aiappsinsightsresponse.py
glean/models/aiinsightsresponse.py
glean/models/announcement.py
glean/models/anonymousevent.py
glean/models/answer.py
glean/models/answerboard.py
glean/models/answercreationdata.py
glean/models/answerlike.py
glean/models/answerlikes.py
glean/models/answerresult.py
glean/models/appresult.py
glean/models/authconfig.py
glean/models/authtoken.py
glean/models/autocompleteop.py
glean/models/autocompleterequest.py
glean/models/autocompleteresponse.py
glean/models/autocompleteresult.py
glean/models/autocompleteresultgroup.py
glean/models/badge.py
glean/models/bulkindexdocumentsrequest.py
glean/models/bulkindexemployeesrequest.py
glean/models/bulkindexgroupsrequest.py
api_client_glean-0.1.0b1.dist-info/METADATA
api_client_glean-0.1.0b1.dist-info/WHEEL
api_client_glean-0.1.0b1.dist-info/RECORD
